cleon_cell_control/__init__.py
cleon_cell_control/_version.py
cleon_cell_control/api.py
cleon_cell_control/labextension/package.json
cleon_cell_control/labextension/static/509.js
cleon_cell_control/labextension/static/remoteEntry.92a6778463b251ac1fee.js
cleon_cell_control/labextension/static/style.js
cleon_cell_control/labextension/static/third-party-licenses.json
cleon_jupyter_extension-0.1.15.data/data/share/jupyter/labextensions/cleon-cell-control/package.json
cleon_jupyter_extension-0.1.15.data/data/share/jupyter/labextensions/cleon-cell-control/static/509.js
cleon_jupyter_extension-0.1.15.data/data/share/jupyter/labextensions/cleon-cell-control/static/remoteEntry.92a6778463b251ac1fee.js
cleon_jupyter_extension-0.1.15.data/data/share/jupyter/labextensions/cleon-cell-control/static/style.js
cleon_jupyter_extension-0.1.15.data/data/share/jupyter/labextensions/cleon-cell-control/static/third-party-licenses.json
cleon_jupyter_extension-0.1.15.dist-info/METADATA
cleon_jupyter_extension-0.1.15.dist-info/WHEEL
cleon_jupyter_extension-0.1.15.dist-info/licenses/LICENSE
cleon_jupyter_extension-0.1.15.dist-info/RECORD
